LICENSE
gitlab_errand_boy/__init__.py
gitlab_errand_boy/__version__.py
gitlab_errand_boy/compound.py
gitlab_errand_boy/sessions.py
gitlab_errand_boy-0.1.12.dist-info/LICENSE
gitlab_errand_boy-0.1.12.dist-info/WHEEL
gitlab_errand_boy-0.1.12.dist-info/METADATA
gitlab_errand_boy-0.1.12.dist-info/RECORD
