Metadata-Version: 2.1
Name: gitlab-errand-boy
Version: 0.1.12
Summary: Run errands with GitLab.
Home-page: https://gitlab.com/buzin.gb/gitlab_errand_boy
License: MIT
Author: Gleb Buzin
Author-email: qufiwefefwoyn@gmail.com
Requires-Python: >=3.8,<4.0
Classifier: License :: OSI Approved :: MIT License
Classifier: Programming Language :: Python :: 3
Classifier: Programming Language :: Python :: 3.8
Classifier: Programming Language :: Python :: 3.9
Requires-Dist: requests (>=2.0.0)
Requires-Dist: tenacity (>=6.0.0)
Project-URL: Repository, https://gitlab.com/buzin.gb/gitlab_errand_boy
